setup.py
planblick.httpserver.egg-info/PKG-INFO
planblick.httpserver.egg-info/SOURCES.txt
planblick.httpserver.egg-info/dependency_links.txt
planblick.httpserver.egg-info/not-zip-safe
planblick.httpserver.egg-info/requires.txt
planblick.httpserver.egg-info/top_level.txt
planblick/httpserver/__init__.py
planblick/httpserver/server.py