Metadata-Version: 1.0
Name: planblick.httpserver
Version: 0.0.11
Summary: A simple class glueing together cherrypi and flask ina streamlined fashion
Home-page: https://www.planblick.com
Author: Florian Kröber @ Planblick
Author-email: fk@planblick.com
License: MIT
Platform: UNKNOWN
